micro_framework/__init__.py
micro_framework/config.py
micro_framework/dependencies.py
micro_framework/entrypoints.py
micro_framework/exceptions.py
micro_framework/extensions.py
micro_framework/metrics.py
micro_framework/retry.py
micro_framework/routes.py
micro_framework/runner.py
micro_framework/standalone.py
micro_framework/targets.py
micro_framework/translators.py
micro_framework/utils.py
micro_framework/workers.py
micro_framework/amqp/__init__.py
micro_framework/amqp/amqp_elements.py
micro_framework/amqp/compressors.py
micro_framework/amqp/connectors.py
micro_framework/amqp/dependencies.py
micro_framework/amqp/entrypoints.py
micro_framework/amqp/exceptions.py
micro_framework/amqp/manager.py
micro_framework/amqp/metrics.py
micro_framework/amqp/rpc.py
micro_framework/amqp/serializers.py
micro_framework/rpc/__init__.py
micro_framework/rpc/client.py
micro_framework/rpc/connectors.py
micro_framework/rpc/dependencies.py
micro_framework/rpc/formatters.py
micro_framework/rpc/manager.py
micro_framework/rpc/proxies.py
micro_framework/spawners/__init__.py
micro_framework/spawners/base.py
micro_framework/spawners/multiprocess.py
micro_framework/spawners/thread.py
micro_framework/websocket/__init__.py
micro_framework/websocket/connectors.py
micro_framework/websocket/dependencies.py
micro_framework/websocket/entrypoints.py
micro_framework/websocket/manager.py
micro_framework/websocket/metrics.py
micro_framework/websocket/rpc.py
micro_framework/websocket/server.py
tests/amqp/__init__.py
tests/rpc/__init__.py
tests/rpc/test_client.py
tests/rpc/test_dependencies.py
tests/rpc/test_formatters.py
tests/rpc/test_manager.py
tests/rpc/test_proxies.py
micro_framework-2.1.0.dist-info/LICENSE
micro_framework-2.1.0.dist-info/METADATA
micro_framework-2.1.0.dist-info/WHEEL
micro_framework-2.1.0.dist-info/top_level.txt
micro_framework-2.1.0.dist-info/RECORD
