Metadata-Version: 2.1
Name: micro-framework
Version: 2.1.0
Summary: Framework to create CPU or IO bound microservices.
Home-page: https://github.com/Mendes11/micro_framework
Author: Rafael Mendes Pacini Bachiega
Author-email: rafaelmpb11@hotmail.com
License: UNKNOWN
Platform: UNKNOWN
Classifier: Intended Audience :: Developers
Classifier: Operating System :: OS Independent
Classifier: Programming Language :: Python :: 3 :: Only
Classifier: Programming Language :: Python :: 3.6
Classifier: Programming Language :: Python :: 3.7
Classifier: Programming Language :: Python :: 3.8
Classifier: Programming Language :: Python :: 3.9
License-File: LICENSE
Requires-Dist: kombu (<6,>=4.6.8)
Requires-Dist: websockets (<9,>=8.1)
Requires-Dist: websocket-client (<1,>=0.57.0)
Requires-Dist: prometheus-client (<0.9)
Requires-Dist: loky (<3,>=2.9.0)
Requires-Dist: psutil
